napari_stpt/__init__.py
napari_stpt/__main__.py
napari_stpt/custom_qt_dims_slider.py
napari_stpt/data.py
napari_stpt/my_widgets.py
napari_stpt/napari_stpt.py
napari_stpt/utilities.py
napari_stpt-0.1.2.6.dist-info/LICENSE
napari_stpt-0.1.2.6.dist-info/METADATA
napari_stpt-0.1.2.6.dist-info/WHEEL
napari_stpt-0.1.2.6.dist-info/entry_points.txt
napari_stpt-0.1.2.6.dist-info/top_level.txt
napari_stpt-0.1.2.6.dist-info/RECORD
