Metadata-Version: 2.1
Name: napari-stpt
Version: 0.1.2.6
Summary: napari viewer which can read stpt, axio and imc images as zarr files
Home-page: https://github.com/TristanWhitmarsh/napari-stpt
Author: Tristan Whitmarsh
Author-email: tw401@cam.ac.uk
License: GNU
Classifier: License :: OSI Approved :: GNU Affero General Public License v3
Classifier: Programming Language :: Python :: 3
License-File: LICENSE
Requires-Dist: opencv-python ==4.5.1.48
Requires-Dist: napari ==0.4.19
Requires-Dist: numpy ==1.24.3
Requires-Dist: xarray ==2023.4.2
Requires-Dist: zarr ==2.14.2
Requires-Dist: PySide2 ==5.13.2
Requires-Dist: SimpleITK ==2.2.1
Requires-Dist: napari-animation ==0.0.7
Requires-Dist: tifffile ==2023.4.12
